pyspark_vector_files/__init__.py
pyspark_vector_files/_files.py
pyspark_vector_files/_parallel_reader.py
pyspark_vector_files/_schema.py
pyspark_vector_files/_types.py
pyspark_vector_files/gpkg.py
pyspark_vector_files-0.2.5.dist-info/WHEEL
pyspark_vector_files-0.2.5.dist-info/LICENSE
pyspark_vector_files-0.2.5.dist-info/METADATA
pyspark_vector_files-0.2.5.dist-info/RECORD
