Metadata-Version: 2.1
Name: pyspark-vector-files
Version: 0.2.5
Summary: Read vector files into a Spark DataFrame with geometry encoded as WKB.
Home-page: https://github.com/Defra-Data-Science-Centre-of-Excellence/pyspark-vector-files
License: MIT
Author: Ed Fawcett-Taylor
Author-email: ed.fawcett-taylor@defra.gov.uk
Requires-Python: >=3.8,<3.9
Classifier: License :: OSI Approved :: MIT License
Classifier: Programming Language :: Python :: 3
Classifier: Programming Language :: Python :: 3.8
Requires-Dist: GDAL (==3.4.3)
Requires-Dist: more-itertools (>=8.12.0,<9.0.0)
Requires-Dist: pandas (>=1.2.4,<2.0.0)
Requires-Dist: pyspark (==3.2.1)
Project-URL: Documentation, https://defra-data-science-centre-of-excellence.github.io/pyspark-vector-files/
Project-URL: Repository, https://github.com/Defra-Data-Science-Centre-of-Excellence/pyspark-vector-files
